Workbook
Name Slicer_Account: #N/A
Name Slicer_Account1: #N/A

Sheet INVOICE
A1: ARSENAULT PRIVATE LIMITED
A3: INVOICE/ ORDER/ BILL ENTRY | I3: GST | J3: 0.18
A5: Order Number | B5: Description | C5: Quantity | D5: Rate | E5: Total Before GST | F5: GST | G5: Total After GST
A6: ED001 | C6: 5 | D6: 1200 | E6: =C6*D6 -> 6000 | F6: =E6*$J$3 -> 1080 | G6: =E6+F6 -> 7080
A7: ED002 | C7: 9 | D7: 13892 | E7: =C7*D7 -> 125028 | F7: =E7*$J$3 -> 22505.04 | G7: =E7+F7 -> 147533.04
A8: ED003 | C8: 12 | D8: 127 | E8: =C8*D8 -> 1524 | F8: =E8*$J$3 -> 274.32 | G8: =E8+F8 -> 1798.32
A9: ED004 | C9: 10 | D9: 652 | E9: =C9*D9 -> 6520 | F9: =E9*$J$3 -> 1173.6 | G9: =E9+F9 -> 7693.6
A10: ED005 | C10: 35 | D10: 5781 | E10: =C10*D10 -> 202335 | F10: =E10*$J$3 -> 36420.3 | G10: =E10+F10 -> 238755.3
A11: ED006 | C11: 21 | D11: 4129 | E11: =C11*D11 -> 86709 | F11: =E11*$J$3 -> 15607.62 | G11: =E11+F11 -> 102316.62
A12: ED007 | C12: 6 | D12: 5121 | E12: =C12*D12 -> 30726 | F12: =E12*$J$3 -> 5530.68 | G12: =E12+F12 -> 36256.68
A13: TOTAL | D13: =SUM(D6:D12) -> 30902 | E13: =SUM(E6:E12) -> 458842 | F13: =SUM(F6:F12) -> 82591.56 | G13: =SUM(G6:G12) -> 541433.56

Sheet CHARTS OF ACCOUNTS
A1: ARSENAULT PRIVATE LIMITED
A3: Chart of Accounts
A4: For the Year 30 June 2025
A5: Account Categories | B5: Sub Account | C5: Label - Financial Statements | D5: Individual Account | E5: Sub Account
A6: Assets | B6: Non-Current Assets | C6: Balance Sheet | D6: Cash | E6: Current Assets
A7: Liabilities | B7: Current Assets | C7: Balance Sheet | D7: Equity | E7: Equity
A8: Equity | B8: Non-Current Liabilities | C8: Balance Sheet | D8: Bank | E8: Current Assets
A9: Expenses | B9: Current Liabilities | C9: Balance Sheet | D9: Inventory | E9: Current Assets
A10: Revenue | B10: Equity | C10: Balance Sheet | D10: Mega Mart - Vendor | E10: Current Liabilities
B11: Expenses | C11: Income Statements | D11: Sale | E11: Revenue
B12: Revenue | C12: Income Statements | D12: Mr. Rehman - Customer | E12: Current Assets
D13: Office Supplies | E13: Expenses
D14: Entertainment Expenses | E14: Expenses
D15: Computer | E15: Non-Current Assets
D16: Salaries | E16: Expenses
D17: Rent | E17: Expenses
D18: Cost of Goods Sold | E18: Expenses
D19: Tax | E19: Expenses
D20: Govt | E20: Current Liabilities

Sheet GENERAL ENTRIES
A2: For the Year June 2025
A3: Date | B3: Desc | C3: Account | D3: Debit | E3: Credit | F3: Details | G3: Entries:
A4: 45839 | B4: Established Business | C4: Cash | D4: 5000000 | F4: Started Business with 5,000,000/- with Cash on 1st July 2023. | G4: 1 | H4: Started Business with 5,000,000/- with Cash on 1st July 2023.
A5: 45839 | B5: Established Business | C5: Equity | E5: =D4 -> 5000000 | G5: 2 | H5: Deposited 1,500,000/- in Bank on 2nd July 2023.
A6: 45840 | B6: Cash Deposited into Bank | C6: Bank | D6: 1500000 | F6: Deposited 1,500,000/- in Bank on 2nd July 2023. | G6: 3 | H6: Inventory purchased of 750,000 on credit from Mega Mart on 5 July 2023.
A7: 45840 | B7: Cash Deposited into Bank | C7: Cash | E7: =D6 -> 1500000 | G7: 4 | H7: Inventory purchased of 500,000 from Multi Media on 7 July 2023.
A8: 45843 | B8: Inventory Purchased | C8: Inventory | D8: 750000 | F8: Inventory purchased of 750,000 on credit from Mega Mart on 5 July 2023. | G8: 5 | H8: Sold inventory on Credit to Mr. Rehman of 400,000 on 10 July 2023.
A9: 45843 | B9: Inventory Purchased | C9: Mega Mart - Vendor | E9: =D8 -> 750000 | G9: 6 | H9: Sold inventory on Cash of 300,000 on 14 July 2023.
A10: 45845 | B10: Inventory Purchased | C10: Inventory | D10: 500000 | F10: Inventory purchased of 500,000 from Multi Media on 7 July 2023. | G10: 7 | H10: Expenses incurred in office of 45,000 on 16 July 2023.
A11: 45845 | B11: Inventory Purchased | C11: Bank | E11: =D10 -> 500000 | G11: 8 | H11: Enertainment Expenses incurred of 70,000 on 18 July 2023.
A12: 45848 | B12: Inventory Sold | C12: Mr. Rehman - Customer | D12: 800000 | F12: Sold inventory on Credit to Mr. Rehman of 400,000 on 10 July 2023. | G12: 9 | H12: Computer purchased for 250,000 On 27 July 2023.
A13: 45848 | B13: Inventory Sold | C13: Sale | E13: =D12 -> 800000 | G13: 10 | H13: Salary Paid on 1st August for 110,000/-
A14: 45852 | B14: Inventory Sold | C14: Cash | D14: 425000 | F14: Sold inventory on Cash of 300,000 on 14 July 2023. | G14: 11 | H14: Rent paid to Mr. Abbas on 2nd Aug of 35,000/-
A15: 45852 | B15: Inventory Sold | C15: Sale | E15: =D14 -> 425000
A16: 45853 | B16: Inventory Adjustment | C16: Cost of Goods Sold | D16: 290000
A17: 45853 | B17: Inventory Adjustment | C17: Inventory | E17: =D16 -> 290000
A18: 45853 | B18: Inventory Adjustment | C18: Cost of Goods Sold | D18: 200000
A19: 45853 | B19: Inventory Adjustment | C19: Inventory | E19: =D18 -> 200000
A20: 45854 | B20: Expenses Incurred | C20: Office Supplies | D20: 45000 | F20: Expenses incurred in office of 45,000 on 16 July 2023.
A21: 45854 | B21: Expenses Incurred | C21: Bank | E21: =D20 -> 45000
A22: 45856 | B22: Entertainment Expenses | C22: Entertainment Expenses | D22: 70000 | F22: Enertainment Expenses incurred of 70,000 on 18 July 2023.
A23: 45856 | B23: Entertainment Expenses | C23: Bank | E23: =D22 -> 70000
A24: 45865 | B24: Computer Purchased | C24: Computer | D24: 250000 | F24: Computer purchased for 250,000 On 27 July 2023.
A25: 45865 | B25: Computer Purchased | C25: Bank | E25: =D24 -> 250000
A26: 45870 | B26: Salaries Paid | C26: Salaries | D26: 110000 | F26: Salary Paid on 1st August for 110,000/-
A27: 45870 | B27: Salaries Paid | C27: Bank | E27: =D26 -> 110000
A28: 45871 | B28: Rent Paid | C28: Rent | D28: 35000 | F28: Rent paid to Mr. Abbas on 2nd Aug of 35,000/-
A29: 45871 | B29: Rent Paid | C29: Bank | E29: =D28 -> 35000
A30: 45871 | B30: Tax Adj | C30: Tax | D30: 142500
A31: 45871 | B31: Tax Adj | C31: Govt | E31: =D30 -> 142500

Sheet LEDGER
A1: LEDGER
A2: =B4 -> Cash
A3: Date | B3: Account | C3: Sum of Debit | D3: Sum of Credit | E3: Sum of Sum of Balance
A4: 45839 | B4: Cash | C4: 5000000 | E4: 5000000
A5: 45839 | B5: Equity | D5: 5000000 | E5: -5000000
A6: 45840 | B6: Bank | C6: 1500000 | E6: 1500000
A7: 45840 | B7: Cash | D7: 1500000 | E7: -1500000
A8: 45843 | B8: Inventory | C8: 750000 | E8: 750000
A9: 45843 | B9: Mega Mart - Vendor | D9: 750000 | E9: -750000
A10: 45845 | B10: Bank | D10: 500000 | E10: -500000
A11: 45845 | B11: Inventory | C11: 500000 | E11: 500000
A12: 45848 | B12: Mr. Rehman - Customer | C12: 800000 | E12: 800000
A13: 45848 | B13: Sale | D13: 800000 | E13: -800000
A14: 45852 | B14: Cash | C14: 425000 | E14: 425000
A15: 45852 | B15: Sale | D15: 425000 | E15: -425000
A16: 45854 | B16: Bank | D16: 45000 | E16: -45000
A17: 45854 | B17: Office Supplies | C17: 45000 | E17: 45000
A18: 45856 | B18: Bank | D18: 70000 | E18: -70000
A19: 45856 | B19: Entertainment Expenses | C19: 70000 | E19: 70000
A20: 45865 | B20: Bank | D20: 250000 | E20: -250000
A21: 45865 | B21: Computer | C21: 250000 | E21: 250000
A22: 45870 | B22: Bank | D22: 110000 | E22: -110000
A23: 45870 | B23: Salaries | C23: 110000 | E23: 110000
A24: 45871 | B24: Bank | D24: 35000 | E24: -35000
A25: 45871 | B25: Rent | C25: 35000 | E25: 35000
A26: 45871 | B26: Tax | C26: 142500 | E26: 142500
A27: 45871 | B27: Govt | D27: 142500 | E27: -142500
A28: 45853 | B28: Inventory | D28: 490000 | E28: -490000
A29: 45853 | B29: Cost of Goods Sold | C29: 490000 | E29: 490000
A30: Grand Total | C30: 10117500 | D30: 10117500 | E30: 0

Sheet TRIAL BALANCE
A1: LEDGER
A2: TRIAL BALANCE
A3: Account | B3: Sum of Debit | C3: Sum of Credit | D3: Sum of Sum of Balance
A4: Bank | B4: 1500000 | C4: 1010000 | D4: 490000 | E4: =VLOOKUP(A4,'CHARTS OF ACCOUNTS'!D:E,2,FALSE) -> Current Assets | F4: Balance Sheet
A5: Cash | B5: 5425000 | C5: 1500000 | D5: 3925000 | E5: =VLOOKUP(A5,'CHARTS OF ACCOUNTS'!D:E,2,FALSE) -> Current Assets | F5: Balance Sheet
A6: Computer | B6: 250000 | D6: 250000 | E6: =VLOOKUP(A6,'CHARTS OF ACCOUNTS'!D:E,2,FALSE) -> Non-Current Assets | F6: Balance Sheet
A7: Entertainment Expenses | B7: 70000 | D7: 70000 | E7: =VLOOKUP(A7,'CHARTS OF ACCOUNTS'!D:E,2,FALSE) -> Expenses | F7: Income Statements
A8: Equity | C8: 5000000 | D8: -5000000 | E8: =VLOOKUP(A8,'CHARTS OF ACCOUNTS'!D:E,2,FALSE) -> Equity | F8: Balance Sheet
A9: Inventory | B9: 1250000 | C9: 490000 | D9: 760000 | E9: =VLOOKUP(A9,'CHARTS OF ACCOUNTS'!D:E,2,FALSE) -> Current Assets | F9: Balance Sheet
A10: Mega Mart - Vendor | C10: 750000 | D10: -750000 | E10: =VLOOKUP(A10,'CHARTS OF ACCOUNTS'!D:E,2,FALSE) -> Current Liabilities | F10: Balance Sheet
A11: Mr. Rehman - Customer | B11: 800000 | D11: 800000 | E11: =VLOOKUP(A11,'CHARTS OF ACCOUNTS'!D:E,2,FALSE) -> Current Assets | F11: Balance Sheet
A12: Office Supplies | B12: 45000 | D12: 45000 | E12: =VLOOKUP(A12,'CHARTS OF ACCOUNTS'!D:E,2,FALSE) -> Expenses | F12: Income Statements
A13: Rent | B13: 35000 | D13: 35000 | E13: =VLOOKUP(A13,'CHARTS OF ACCOUNTS'!D:E,2,FALSE) -> Expenses | F13: Income Statements
A14: Salaries | B14: 110000 | D14: 110000 | E14: =VLOOKUP(A14,'CHARTS OF ACCOUNTS'!D:E,2,FALSE) -> Expenses | F14: Income Statements
A15: Sale | C15: 1225000 | D15: -1225000 | E15: =VLOOKUP(A15,'CHARTS OF ACCOUNTS'!D:E,2,FALSE) -> Revenue | F15: Income Statements
A16: Cost of Goods Sold | B16: 490000 | D16: 490000 | E16: =VLOOKUP(A16,'CHARTS OF ACCOUNTS'!D:E,2,FALSE) -> Expenses | F16: Income Statements
A17: Tax | B17: 142500 | D17: 142500
A18: Govt | C18: 142500 | D18: -142500
A19: Grand Total | B19: 10117500 | C19: 10117500 | D19: 0
